setup.cfg
setup.py
sieve_sift.egg-info/PKG-INFO
sieve_sift.egg-info/SOURCES.txt
sieve_sift.egg-info/dependency_links.txt
sieve_sift.egg-info/requires.txt
sieve_sift.egg-info/top_level.txt
sift/__init__.py
sift/image_compare.py
sift/sift
sift/sift.py
sift/tests/__init__.py
sift/tests/test_sift.py