Metadata-Version: 1.0
Name: sieve-sift
Version: 0.1.6
Summary: Sieve sift module.
Home-page: https://bitbucket.org/sievetech
Author: Sieve
Author-email: sievetech@sieve.com.br
License: UNKNOWN
Platform: UNKNOWN
